ConfigHelper/ConfigHelper.py
ConfigHelper/__init__.py
ConfigHelper-0.0.3.dist-info/LICENSE
ConfigHelper-0.0.3.dist-info/METADATA
ConfigHelper-0.0.3.dist-info/WHEEL
ConfigHelper-0.0.3.dist-info/top_level.txt
ConfigHelper-0.0.3.dist-info/RECORD
