Metadata-Version: 2.1
Name: ConfigHelper
Version: 0.0.3
Summary: Can use it to save or recall preferences from Python.
Home-page: https://github.com/Sotaneum/ConfigHelper
Author: Donggun LEE
Author-email: gnyotnu39@gmail.com
License: UNKNOWN
Platform: UNKNOWN
Classifier: License :: OSI Approved :: MIT License
